{"specific_stats": {"1999": {"Clay": ["Singles Service Record", "Aces 0", "Double Faults 0", "1st Serve 0%", "1st Serve Points Won 0%", "2nd Serve Points Won 0%", "Break Points Faced 0", "Break Points Saved 0%", "Service Games Played 0", "Service Games Won 0%", "Total Service Points Won 0%", "Singles Return Record", "1st Serve Return Points Won 0%", "2nd Serve Return Points Won 0%", "Break Points Opportunities 0", "Break Points Converted 0%", "Return Games Played 0", "Return Games Won 0%", "Return Points Won 0%", "Total Points Won 0%"], "Carpet": ["No Player Stats", "We do not have any stats for this player."], "Hard": ["Singles Service Record", "Aces 5", "Double Faults 2", "1st Serve 63%", "1st Serve Points Won 63%", "2nd Serve Points Won 32%", "Break Points Faced 22", "Break Points Saved 82%", "Service Games Played 9", "Service Games Won 56%", "Total Service Points Won 52%", "Singles Return Record", "1st Serve Return Points Won 8%", "2nd Serve Return Points Won 43%", "Break Points Opportunities 0", "Break Points Converted 0%", "Return Games Played 8", "Return Games Won 0%", "Return Points Won 24%", "Total Points Won 43%"], "all": ["Singles Service Record", "Aces 5", "Double Faults 2", "1st Serve 63%", "1st Serve Points Won 63%", "2nd Serve Points Won 32%", "Break Points Faced 22", "Break Points Saved 82%", "Service Games Played 9", "Service Games Won 56%", "Total Service Points Won 52%", "Singles Return Record", "1st Serve Return Points Won 8%", "2nd Serve Return Points Won 43%", "Break Points Opportunities 0", "Break Points Converted 0%", "Return Games Played 8", "Return Games Won 0%", "Return Points Won 24%", "Total Points Won 43%"], "Grass": ["No Player Stats", "We do not have any stats for this player."]}, "2003": {"Clay": ["No Player Stats", "We do not have any stats for this player."], "Carpet": ["Singles Service Record", "Aces 0", "Double Faults 0", "1st Serve 0%", "1st Serve Points Won 0%", "2nd Serve Points Won 0%", "Break Points Faced 0", "Break Points Saved 0%", "Service Games Played 0", "Service Games Won 0%", "Total Service Points Won 0%", "Singles Return Record", "1st Serve Return Points Won 0%", "2nd Serve Return Points Won 0%", "Break Points Opportunities 0", "Break Points Converted 0%", "Return Games Played 0", "Return Games Won 0%", "Return Points Won 0%", "Total Points Won 0%"], "Hard": ["Singles Service Record", "Aces 39", "Double Faults 17", "1st Serve 60%", "1st Serve Points Won 70%", "2nd Serve Points Won 51%", "Break Points Faced 26", "Break Points Saved 42%", "Service Games Played 60", "Service Games Won 75%", "Total Service Points Won 62%", "Singles Return Record", "1st Serve Return Points Won 28%", "2nd Serve Return Points Won 50%", "Break Points Opportunities 37", "Break Points Converted 24%", "Return Games Played 60", "Return Games Won 15%", "Return Points Won 36%", "Total Points Won 49%"], "all": ["Singles Service Record", "Aces 39", "Double Faults 17", "1st Serve 60%", "1st Serve Points Won 70%", "2nd Serve Points Won 51%", "Break Points Faced 26", "Break Points Saved 42%", "Service Games Played 60", "Service Games Won 75%", "Total Service Points Won 62%", "Singles Return Record", "1st Serve Return Points Won 28%", "2nd Serve Return Points Won 50%", "Break Points Opportunities 37", "Break Points Converted 24%", "Return Games Played 60", "Return Games Won 15%", "Return Points Won 36%", "Total Points Won 49%"], "Grass": ["No Player Stats", "We do not have any stats for this player."]}, "2004": {"Clay": ["Singles Service Record", "Aces 0", "Double Faults 0", "1st Serve 0%", "1st Serve Points Won 0%", "2nd Serve Points Won 0%", "Break Points Faced 0", "Break Points Saved 0%", "Service Games Played 0", "Service Games Won 0%", "Total Service Points Won 0%", "Singles Return Record", "1st Serve Return Points Won 0%", "2nd Serve Return Points Won 0%", "Break Points Opportunities 0", "Break Points Converted 0%", "Return Games Played 0", "Return Games Won 0%", "Return Points Won 0%", "Total Points Won 0%"], "Carpet": ["No Player Stats", "We do not have any stats for this player."], "Hard": ["Singles Service Record", "Aces 7", "Double Faults 9", "1st Serve 55%", "1st Serve Points Won 62%", "2nd Serve Points Won 48%", "Break Points Faced 34", "Break Points Saved 65%", "Service Games Played 32", "Service Games Won 63%", "Total Service Points Won 56%", "Singles Return Record", "1st Serve Return Points Won 33%", "2nd Serve Return Points Won 46%", "Break Points Opportunities 16", "Break Points Converted 56%", "Return Games Played 33", "Return Games Won 27%", "Return Points Won 38%", "Total Points Won 48%"], "all": ["Singles Service Record", "Aces 7", "Double Faults 9", "1st Serve 55%", "1st Serve Points Won 62%", "2nd Serve Points Won 48%", "Break Points Faced 34", "Break Points Saved 65%", "Service Games Played 32", "Service Games Won 63%", "Total Service Points Won 56%", "Singles Return Record", "1st Serve Return Points Won 33%", "2nd Serve Return Points Won 46%", "Break Points Opportunities 16", "Break Points Converted 56%", "Return Games Played 33", "Return Games Won 27%", "Return Points Won 38%", "Total Points Won 48%"], "Grass": ["No Player Stats", "We do not have any stats for this player."]}, "2001": {"Clay": ["Singles Service Record", "Aces 0", "Double Faults 0", "1st Serve 0%", "1st Serve Points Won 0%", "2nd Serve Points Won 0%", "Break Points Faced 0", "Break Points Saved 0%", "Service Games Played 0", "Service Games Won 0%", "Total Service Points Won 0%", "Singles Return Record", "1st Serve Return Points Won 0%", "2nd Serve Return Points Won 0%", "Break Points Opportunities 0", "Break Points Converted 0%", "Return Games Played 0", "Return Games Won 0%", "Return Points Won 0%", "Total Points Won 0%"], "Carpet": ["No Player Stats", "We do not have any stats for this player."], "Hard": ["Singles Service Record", "Aces 6", "Double Faults 3", "1st Serve 57%", "1st Serve Points Won 52%", "2nd Serve Points Won 54%", "Break Points Faced 12", "Break Points Saved 50%", "Service Games Played 14", "Service Games Won 57%", "Total Service Points Won 53%", "Singles Return Record", "1st Serve Return Points Won 30%", "2nd Serve Return Points Won 32%", "Break Points Opportunities 2", "Break Points Converted 100%", "Return Games Played 13", "Return Games Won 15%", "Return Points Won 31%", "Total Points Won 43%"], "all": ["Singles Service Record", "Aces 6", "Double Faults 3", "1st Serve 57%", "1st Serve Points Won 52%", "2nd Serve Points Won 54%", "Break Points Faced 12", "Break Points Saved 50%", "Service Games Played 14", "Service Games Won 57%", "Total Service Points Won 53%", "Singles Return Record", "1st Serve Return Points Won 30%", "2nd Serve Return Points Won 32%", "Break Points Opportunities 2", "Break Points Converted 100%", "Return Games Played 13", "Return Games Won 15%", "Return Points Won 31%", "Total Points Won 43%"], "Grass": ["No Player Stats", "We do not have any stats for this player."]}, "2000": {"Clay": ["Singles Service Record", "Aces 0", "Double Faults 0", "1st Serve 0%", "1st Serve Points Won 0%", "2nd Serve Points Won 0%", "Break Points Faced 0", "Break Points Saved 0%", "Service Games Played 0", "Service Games Won 0%", "Total Service Points Won 0%", "Singles Return Record", "1st Serve Return Points Won 0%", "2nd Serve Return Points Won 0%", "Break Points Opportunities 0", "Break Points Converted 0%", "Return Games Played 0", "Return Games Won 0%", "Return Points Won 0%", "Total Points Won 0%"], "Carpet": ["No Player Stats", "We do not have any stats for this player."], "Hard": ["Singles Service Record", "Aces 14", "Double Faults 7", "1st Serve 60%", "1st Serve Points Won 65%", "2nd Serve Points Won 44%", "Break Points Faced 13", "Break Points Saved 38%", "Service Games Played 21", "Service Games Won 62%", "Total Service Points Won 57%", "Singles Return Record", "1st Serve Return Points Won 32%", "2nd Serve Return Points Won 50%", "Break Points Opportunities 8", "Break Points Converted 50%", "Return Games Played 20", "Return Games Won 20%", "Return Points Won 39%", "Total Points Won 48%"], "all": ["Singles Service Record", "Aces 14", "Double Faults 7", "1st Serve 60%", "1st Serve Points Won 65%", "2nd Serve Points Won 44%", "Break Points Faced 13", "Break Points Saved 38%", "Service Games Played 21", "Service Games Won 62%", "Total Service Points Won 57%", "Singles Return Record", "1st Serve Return Points Won 32%", "2nd Serve Return Points Won 50%", "Break Points Opportunities 8", "Break Points Converted 50%", "Return Games Played 20", "Return Games Won 20%", "Return Points Won 39%", "Total Points Won 48%"], "Grass": ["No Player Stats", "We do not have any stats for this player."]}, "0": {"Clay": ["No Player Stats", "We do not have any stats for this player."], "Carpet": ["No Player Stats", "We do not have any stats for this player."], "Hard": ["Singles Service Record", "Aces 71", "Double Faults 39", "1st Serve 59%", "1st Serve Points Won 65%", "2nd Serve Points Won 47%", "Break Points Faced 116", "Break Points Saved 58%", "Service Games Played 143", "Service Games Won 66%", "Total Service Points Won 57%", "Singles Return Record", "1st Serve Return Points Won 28%", "2nd Serve Return Points Won 46%", "Break Points Opportunities 63", "Break Points Converted 38%", "Return Games Played 142", "Return Games Won 17%", "Return Points Won 35%", "Total Points Won 47%"], "all": ["Singles Service Record", "Aces 71", "Double Faults 39", "1st Serve 59%", "1st Serve Points Won 65%", "2nd Serve Points Won 47%", "Break Points Faced 116", "Break Points Saved 58%", "Service Games Played 143", "Service Games Won 66%", "Total Service Points Won 57%", "Singles Return Record", "1st Serve Return Points Won 28%", "2nd Serve Return Points Won 46%", "Break Points Opportunities 63", "Break Points Converted 38%", "Return Games Played 142", "Return Games Won 17%", "Return Points Won 35%", "Total Points Won 47%"], "Grass": ["No Player Stats", "We do not have any stats for this player."]}, "2002": {"Clay": ["No Player Stats", "We do not have any stats for this player."], "Carpet": ["Singles Service Record", "Aces 0", "Double Faults 0", "1st Serve 0%", "1st Serve Points Won 0%", "2nd Serve Points Won 0%", "Break Points Faced 0", "Break Points Saved 0%", "Service Games Played 0", "Service Games Won 0%", "Total Service Points Won 0%", "Singles Return Record", "1st Serve Return Points Won 0%", "2nd Serve Return Points Won 0%", "Break Points Opportunities 0", "Break Points Converted 0%", "Return Games Played 0", "Return Games Won 0%", "Return Points Won 0%", "Total Points Won 0%"], "Hard": ["Singles Service Record", "Aces 0", "Double Faults 1", "1st Serve 54%", "1st Serve Points Won 54%", "2nd Serve Points Won 41%", "Break Points Faced 9", "Break Points Saved 56%", "Service Games Played 7", "Service Games Won 43%", "Total Service Points Won 48%", "Singles Return Record", "1st Serve Return Points Won 9%", "2nd Serve Return Points Won 28%", "Break Points Opportunities 0", "Break Points Converted 0%", "Return Games Played 8", "Return Games Won 0%", "Return Points Won 18%", "Total Points Won 34%"], "all": ["Singles Service Record", "Aces 0", "Double Faults 1", "1st Serve 54%", "1st Serve Points Won 54%", "2nd Serve Points Won 41%", "Break Points Faced 9", "Break Points Saved 56%", "Service Games Played 7", "Service Games Won 43%", "Total Service Points Won 48%", "Singles Return Record", "1st Serve Return Points Won 9%", "2nd Serve Return Points Won 28%", "Break Points Opportunities 0", "Break Points Converted 0%", "Return Games Played 8", "Return Games Won 0%", "Return Points Won 18%", "Total Points Won 34%"], "Grass": ["No Player Stats", "We do not have any stats for this player."]}}, "global_desc": ["Simon", "Larose", "Inactive", "  CAN", "DOB", "(1978.06.28)", "Turned Pro 1998", "Weight 190Lbs(86kg)", "Height 6'3\"(191cm)", "Birthplace Cap-de-la-Madeleine, Canada", "Residence Cap-de-la-Madeleine, Canada", "Plays Right-Handed", "Coach Martin Laurendeau"], "bio": ["No Bio Available", "Unfortunately, we do not currently have any bio information for this player"]}