{"specific_stats": {"0": {"Carpet": ["No Player Stats", "We do not have any stats for this player."], "all": ["Singles Service Record", "Aces 5", "Double Faults 3", "1st Serve 67%", "1st Serve Points Won 65%", "2nd Serve Points Won 46%", "Break Points Faced 28", "Break Points Saved 54%", "Service Games Played 39", "Service Games Won 67%", "Total Service Points Won 59%", "Singles Return Record", "1st Serve Return Points Won 17%", "2nd Serve Return Points Won 45%", "Break Points Opportunities 12", "Break Points Converted 42%", "Return Games Played 40", "Return Games Won 13%", "Return Points Won 28%", "Total Points Won 44%"], "Clay": ["No Player Stats", "We do not have any stats for this player."], "Hard": ["Singles Service Record", "Aces 5", "Double Faults 2", "1st Serve 65%", "1st Serve Points Won 69%", "2nd Serve Points Won 50%", "Break Points Faced 15", "Break Points Saved 40%", "Service Games Played 30", "Service Games Won 70%", "Total Service Points Won 62%", "Singles Return Record", "1st Serve Return Points Won 15%", "2nd Serve Return Points Won 47%", "Break Points Opportunities 11", "Break Points Converted 36%", "Return Games Played 30", "Return Games Won 13%", "Return Points Won 29%", "Total Points Won 45%"], "Grass": ["Singles Service Record", "Aces 0", "Double Faults 1", "1st Serve 70%", "1st Serve Points Won 59%", "2nd Serve Points Won 38%", "Break Points Faced 13", "Break Points Saved 69%", "Service Games Played 9", "Service Games Won 56%", "Total Service Points Won 53%", "Singles Return Record", "1st Serve Return Points Won 22%", "2nd Serve Return Points Won 36%", "Break Points Opportunities 1", "Break Points Converted 100%", "Return Games Played 10", "Return Games Won 10%", "Return Points Won 25%", "Total Points Won 42%"]}, "2018": {"Carpet": ["No Player Stats", "We do not have any stats for this player."], "all": ["Singles Service Record", "Aces 4", "Double Faults 1", "1st Serve 68%", "1st Serve Points Won 70%", "2nd Serve Points Won 51%", "Break Points Faced 11", "Break Points Saved 45%", "Service Games Played 22", "Service Games Won 73%", "Total Service Points Won 64%", "Singles Return Record", "1st Serve Return Points Won 19%", "2nd Serve Return Points Won 49%", "Break Points Opportunities 9", "Break Points Converted 44%", "Return Games Played 21", "Return Games Won 19%", "Return Points Won 34%", "Total Points Won 49%"], "Clay": ["No Player Stats", "We do not have any stats for this player."], "Hard": ["Singles Service Record", "Aces 4", "Double Faults 1", "1st Serve 68%", "1st Serve Points Won 70%", "2nd Serve Points Won 51%", "Break Points Faced 11", "Break Points Saved 45%", "Service Games Played 22", "Service Games Won 73%", "Total Service Points Won 64%", "Singles Return Record", "1st Serve Return Points Won 19%", "2nd Serve Return Points Won 49%", "Break Points Opportunities 9", "Break Points Converted 44%", "Return Games Played 21", "Return Games Won 19%", "Return Points Won 34%", "Total Points Won 49%"], "Grass": ["No Player Stats", "We do not have any stats for this player."]}, "2017": {"Carpet": ["No Player Stats", "We do not have any stats for this player."], "all": ["Singles Service Record", "Aces 1", "Double Faults 2", "1st Serve 65%", "1st Serve Points Won 61%", "2nd Serve Points Won 41%", "Break Points Faced 17", "Break Points Saved 59%", "Service Games Played 17", "Service Games Won 59%", "Total Service Points Won 54%", "Singles Return Record", "1st Serve Return Points Won 15%", "2nd Serve Return Points Won 36%", "Break Points Opportunities 3", "Break Points Converted 33%", "Return Games Played 19", "Return Games Won 5%", "Return Points Won 21%", "Total Points Won 39%"], "Clay": ["No Player Stats", "We do not have any stats for this player."], "Hard": ["Singles Service Record", "Aces 1", "Double Faults 1", "1st Serve 55%", "1st Serve Points Won 67%", "2nd Serve Points Won 47%", "Break Points Faced 4", "Break Points Saved 25%", "Service Games Played 8", "Service Games Won 63%", "Total Service Points Won 58%", "Singles Return Record", "1st Serve Return Points Won 9%", "2nd Serve Return Points Won 36%", "Break Points Opportunities 2", "Break Points Converted 0%", "Return Games Played 9", "Return Games Won 0%", "Return Points Won 16%", "Total Points Won 35%"], "Grass": ["Singles Service Record", "Aces 0", "Double Faults 1", "1st Serve 70%", "1st Serve Points Won 59%", "2nd Serve Points Won 38%", "Break Points Faced 13", "Break Points Saved 69%", "Service Games Played 9", "Service Games Won 56%", "Total Service Points Won 53%", "Singles Return Record", "1st Serve Return Points Won 22%", "2nd Serve Return Points Won 36%", "Break Points Opportunities 1", "Break Points Converted 100%", "Return Games Played 10", "Return Games Won 10%", "Return Points Won 25%", "Total Points Won 42%"]}}, "global_desc": ["Tallon", "Griekspoor", "#Singles#", "Ranking", "228", "NED", "Age 21", "(1996.07.02)", "Turned Pro", "Weight 181Lbs(82kg)", "Height 6'2\"(188cm)", "Birthplace Haarlem, Netherlands", "Residence Nieuw Vennep, Netherlands", "Plays Right-Handed, Two-Handed Backhand", "Coach Kristof Vliegen"], "bio": ["Player Bio", "Year By Year", "2017 -- Dutchman made ATP World Tour debut on home soil at Rotterdam as WC (l. to Muller in 1R)...Qualified in doubles at Rotterdam w/Lootsma (l. to Lopez/Lopez in 1R)...Achieved career-high No. 282 in Emirates ATP Rankings on June 12...Did not drop a set en route to 3rd ITF Futures Circuit title at Manama, BRN (d. Konecny)...Advanced to back-to-back Futures finals in Antalya at Turkey F2 (l. to Lazov) and Turkey F3 (ret vs Ilkel)...Captured Heraklion, GRE Futures doubles title w/K. Griekspoor (d. Gabb/Johnson)"]}