{"global_desc": ["Vaclav", "Safranek", "#Singles#", "Ranking", "216", "CZE", "Age 23", "(1994.05.20)", "Turned Pro 2012", "Weight 176Lbs(80kg)", "Height 6'1\"(185cm)", "Birthplace Brno, Czech Republic", "Residence Brno, Czech Republic", "Plays Right-Handed, Two-Handed Backhand", "Coach Petr Frelich"], "bio": ["Player Bio", "Personal Year By Year Career", "> Nickname is \"Venca\".", "> Speaks Czech and English.", "> Father, Petr, is a tennis coach; mother, Martina, is a teacher; brother, Stepan.", "> Started playing tennis at age 5 with his father.", "> Favourite surface is clay, shot is forehand and tournament is US Open.", "> Idols growing up were Marat Safin and Andre Agassi.", "> Enjoys going to the movies and watching sports.", "> Supports HC Kometa Brno (ice hockey) and Real Madrid (football).", "> Trains at his family club, TC Brno.", "> Fitness trainer is David Nerud.", " "], "specific_stats": {"2018": {"Grass": ["No Player Stats", "We do not have any stats for this player."], "all": ["Singles Service Record", "Aces 1", "Double Faults 0", "1st Serve 69%", "1st Serve Points Won 63%", "2nd Serve Points Won 62%", "Break Points Faced 6", "Break Points Saved 33%", "Service Games Played 14", "Service Games Won 71%", "Total Service Points Won 62%", "Singles Return Record", "1st Serve Return Points Won 26%", "2nd Serve Return Points Won 29%", "Break Points Opportunities 5", "Break Points Converted 0%", "Return Games Played 14", "Return Games Won 0%", "Return Points Won 27%", "Total Points Won 44%"], "Carpet": ["No Player Stats", "We do not have any stats for this player."], "Hard": ["Singles Service Record", "Aces 1", "Double Faults 0", "1st Serve 69%", "1st Serve Points Won 63%", "2nd Serve Points Won 62%", "Break Points Faced 6", "Break Points Saved 33%", "Service Games Played 14", "Service Games Won 71%", "Total Service Points Won 62%", "Singles Return Record", "1st Serve Return Points Won 26%", "2nd Serve Return Points Won 29%", "Break Points Opportunities 5", "Break Points Converted 0%", "Return Games Played 14", "Return Games Won 0%", "Return Points Won 27%", "Total Points Won 44%"], "Clay": ["No Player Stats", "We do not have any stats for this player."]}, "0": {"Grass": ["No Player Stats", "We do not have any stats for this player."], "all": ["Singles Service Record", "Aces 5", "Double Faults 6", "1st Serve 65%", "1st Serve Points Won 61%", "2nd Serve Points Won 51%", "Break Points Faced 21", "Break Points Saved 57%", "Service Games Played 26", "Service Games Won 65%", "Total Service Points Won 57%", "Singles Return Record", "1st Serve Return Points Won 23%", "2nd Serve Return Points Won 33%", "Break Points Opportunities 9", "Break Points Converted 0%", "Return Games Played 27", "Return Games Won 0%", "Return Points Won 27%", "Total Points Won 43%"], "Carpet": ["No Player Stats", "We do not have any stats for this player."], "Hard": ["Singles Service Record", "Aces 5", "Double Faults 6", "1st Serve 65%", "1st Serve Points Won 61%", "2nd Serve Points Won 51%", "Break Points Faced 21", "Break Points Saved 57%", "Service Games Played 26", "Service Games Won 65%", "Total Service Points Won 57%", "Singles Return Record", "1st Serve Return Points Won 23%", "2nd Serve Return Points Won 33%", "Break Points Opportunities 9", "Break Points Converted 0%", "Return Games Played 27", "Return Games Won 0%", "Return Points Won 27%", "Total Points Won 43%"], "Clay": ["No Player Stats", "We do not have any stats for this player."]}, "2017": {"Grass": ["No Player Stats", "We do not have any stats for this player."], "all": ["Singles Service Record", "Aces 4", "Double Faults 6", "1st Serve 61%", "1st Serve Points Won 59%", "2nd Serve Points Won 43%", "Break Points Faced 15", "Break Points Saved 67%", "Service Games Played 12", "Service Games Won 58%", "Total Service Points Won 53%", "Singles Return Record", "1st Serve Return Points Won 20%", "2nd Serve Return Points Won 36%", "Break Points Opportunities 4", "Break Points Converted 0%", "Return Games Played 13", "Return Games Won 0%", "Return Points Won 27%", "Total Points Won 41%"], "Carpet": ["No Player Stats", "We do not have any stats for this player."], "Hard": ["Singles Service Record", "Aces 4", "Double Faults 6", "1st Serve 61%", "1st Serve Points Won 59%", "2nd Serve Points Won 43%", "Break Points Faced 15", "Break Points Saved 67%", "Service Games Played 12", "Service Games Won 58%", "Total Service Points Won 53%", "Singles Return Record", "1st Serve Return Points Won 20%", "2nd Serve Return Points Won 36%", "Break Points Opportunities 4", "Break Points Converted 0%", "Return Games Played 13", "Return Games Won 0%", "Return Points Won 27%", "Total Points Won 41%"], "Clay": ["No Player Stats", "We do not have any stats for this player."]}}}