{"global_desc": ["Yuichi", "Ito", "#Doubles#", "Ranking", "633", "JPN", "Age 31", "(1986.08.06)", "Turned Pro", "Weight", "Height", "Birthplace", "Residence", "Plays", "Coach"], "specific_stats": {"2008": {"Carpet": ["No Player Stats", "We do not have any stats for this player."], "Hard": ["Singles Service Record", "Aces 1", "Double Faults 0", "1st Serve 66%", "1st Serve Points Won 57%", "2nd Serve Points Won 39%", "Break Points Faced 6", "Break Points Saved 33%", "Service Games Played 8", "Service Games Won 50%", "Total Service Points Won 51%", "Singles Return Record", "1st Serve Return Points Won 31%", "2nd Serve Return Points Won 33%", "Break Points Opportunities 3", "Break Points Converted 33%", "Return Games Played 9", "Return Games Won 11%", "Return Points Won 32%", "Total Points Won 41%"], "Clay": ["No Player Stats", "We do not have any stats for this player."], "all": ["Singles Service Record", "Aces 1", "Double Faults 0", "1st Serve 66%", "1st Serve Points Won 57%", "2nd Serve Points Won 39%", "Break Points Faced 6", "Break Points Saved 33%", "Service Games Played 8", "Service Games Won 50%", "Total Service Points Won 51%", "Singles Return Record", "1st Serve Return Points Won 31%", "2nd Serve Return Points Won 33%", "Break Points Opportunities 3", "Break Points Converted 33%", "Return Games Played 9", "Return Games Won 11%", "Return Points Won 32%", "Total Points Won 41%"], "Grass": ["No Player Stats", "We do not have any stats for this player."]}, "0": {"Carpet": ["No Player Stats", "We do not have any stats for this player."], "Hard": ["Singles Service Record", "Aces 1", "Double Faults 0", "1st Serve 66%", "1st Serve Points Won 57%", "2nd Serve Points Won 39%", "Break Points Faced 6", "Break Points Saved 33%", "Service Games Played 8", "Service Games Won 50%", "Total Service Points Won 51%", "Singles Return Record", "1st Serve Return Points Won 31%", "2nd Serve Return Points Won 33%", "Break Points Opportunities 3", "Break Points Converted 33%", "Return Games Played 9", "Return Games Won 11%", "Return Points Won 32%", "Total Points Won 41%"], "Clay": ["No Player Stats", "We do not have any stats for this player."], "all": ["Singles Service Record", "Aces 1", "Double Faults 0", "1st Serve 66%", "1st Serve Points Won 57%", "2nd Serve Points Won 39%", "Break Points Faced 6", "Break Points Saved 33%", "Service Games Played 8", "Service Games Won 50%", "Total Service Points Won 51%", "Singles Return Record", "1st Serve Return Points Won 31%", "2nd Serve Return Points Won 33%", "Break Points Opportunities 3", "Break Points Converted 33%", "Return Games Played 9", "Return Games Won 11%", "Return Points Won 32%", "Total Points Won 41%"], "Grass": ["No Player Stats", "We do not have any stats for this player."]}}}